karrio/mappers/yunexpress/__init__.py
karrio/mappers/yunexpress/mapper.py
karrio/mappers/yunexpress/proxy.py
karrio/mappers/yunexpress/settings.py
karrio/providers/yunexpress/__init__.py
karrio/providers/yunexpress/error.py
karrio/providers/yunexpress/tracking.py
karrio/providers/yunexpress/units.py
karrio/providers/yunexpress/utils.py
karrio.yunexpress-2023.4.dist-info/METADATA
karrio.yunexpress-2023.4.dist-info/WHEEL
karrio.yunexpress-2023.4.dist-info/top_level.txt
karrio.yunexpress-2023.4.dist-info/RECORD
